.gitignore
.readthedocs.yaml
CONTRIBUTING.md
LICENSE
Makefile
README.md
pyproject.toml
setup.py
.github/dependabot.yml
.github/ISSUE_TEMPLATE/bug_report.md
.github/ISSUE_TEMPLATE/custom.md
.github/ISSUE_TEMPLATE/feature_request.md
.github/workflows/build.yml
CryptoRL.egg-info/PKG-INFO
CryptoRL.egg-info/SOURCES.txt
CryptoRL.egg-info/dependency_links.txt
CryptoRL.egg-info/requires.txt
CryptoRL.egg-info/top_level.txt
cryptorl/__init__.py
cryptorl/data.py
cryptorl/env_crypto.py
cryptorl/predict_DT.py
cryptorl/predict_LR.py
cryptorl/predict_NN.py
cryptorl/utils.py
cryptorl/tests/integration_test.py
cryptorl/tests/unit_test.py
docs/Makefile
docs/conf.py
docs/index.rst
docs/make.bat
docs/requirements.txt
docs/source/cryptorl.rst
docs/source/example.rst
docs/source/modules.rst