Metadata-Version: 2.1
Name: CryptoRL
Version: 0.2.0
Summary: Fetching time series data of cryptocurrencies and using ML and RL to do cryptocurrency trading.
Author-email: Ziyi Xia <zx2325@columbia.edu>
License: MIT License
Project-URL: repository, https://github.com/ZiyiXia/CryptoRL
Classifier: Development Status :: 2 - Pre-Alpha
Classifier: Programming Language :: Python :: Implementation :: CPython
Classifier: Programming Language :: Python :: Implementation :: PyPy
Classifier: Programming Language :: Python :: 3
Classifier: Programming Language :: Python :: 3.7
Classifier: Programming Language :: Python :: 3.8
Classifier: Programming Language :: Python :: 3.9
Classifier: Programming Language :: Python :: 3.10
Classifier: Programming Language :: Python :: 3.11
Requires-Python: >=3.7
Provides-Extra: develop
License-File: LICENSE
